{
	"name": "OxTheme",
	"colors": {
		"editor.background": "#000000",
		"editor.foreground": "#a7a7a7",
		"editorLineNumber.foreground": "#4b4b4b",
		"editorCursor.foreground": "#ffffff",

		"editor.selectionBackground": "#0055a0",
		"editor.selectionForeground": "#ffffff",
		"editor.selectionHighlightBorder": "#d7d7d7",
		"editor.inactiveSelectionBackground": "#000000",
		"editor.selectionHighlightBackground": "#000000",

		"editor.hoverHighlightBackground": "#000000",
		"editor.lineHighlightBackground": "#171717",
		"editor.lineHighlightBorder": "#171717",

		"window.activeBorder": "#ffffff",
		"window.inactiveBorder": "#ffffff",

		"selection.background": "#000000",

		"editorBracketMatch.background": "#6b6b6b",
		"editorBracketMatch.border": "#000000",
		"editorBracketHighlight.foreground1": "#ffffff",
		"editorBracketHighlight.foreground2": "#ffffff",
		"editorBracketHighlight.foreground3": "#ffffff",
		"editorBracketHighlight.foreground4": "#ffffff",
		"editorBracketHighlight.foreground5": "#ffffff",
		"editorBracketHighlight.foreground6": "#ffffff",

		"activityBarBadge.background": "#d9ff00",
		"activityBarBadge.foreground": "#000000",
		"sideBar.background": "#000000",
		"sideBar.foreground": "#bcbcbc",
		"sideBar.border": "#232323",
		"sideBarTitle.foreground": "#c5c5c5",
		"sideBarSectionHeader.background": "#000000",
		"sideBarSectionHeader.foreground": "#c5c5c5",
		"sideBarSectionHeader.border": "#232323",
		"statusBar.background": "#000000",
		"statusBar.foreground": "#a1a1a1",
		"titleBar.activeBackground": "#000000",
		"titleBar.activeForeground": "#ffffff",
		"titleBar.inactiveBackground": "#000000",
		"titleBar.inactiveForeground": "#bfbfbf",

		"menubar.selectionForeground": "#ffffff",
		"menubar.selectionBackground": "#1e1e1e",
		"menubar.selectionBorder": "#000000",
		"menu.foreground": "#c7c7c7",
		"menu.background": "#1e1e1e",
		"menu.selectionForeground": "#ffffff",
		"menu.selectionBackground": "#1e1e1e",
		"menu.separatorBackground": "#1e1e1e",
		"commandCenter.foreground": "#ffffff",
		"commandCenter.background": "#000000",

		"scrollbar.shadow": "#00000000",
		"scrollbarSlider.activeBackground": "#ffffff",
		"scrollbarSlider.background": "#ff000000",
		"scrollbarSlider.hoverBackground": "#3e3e3e",

		"notificationCenter.border": "#000000",
		"notificationCenterHeader.background": "#000000",
		"notificationCenterHeader.foreground": "#ffffff",
		"notifications.foreground": "#ffffff",
		"notifications.background": "#000000",
		"notifications.border": "#000000",
		"notificationToast.border": "#000000",

		"activityBar.foreground": "#ffffff",
		"activityBar.background": "#000000",
		"activityBar.border": "#23232300",

		"tab.activeBackground": "#000000",
		"tab.unfocusedActiveBackground": "#000000",
		"tab.activeForeground": "#ffffff",
		"tab.border": "#000000",
		"tab.activeBorder": "#ffffff",
		"tab.unfocusedActiveBorder": "#ffffff",
		"tab.activeBorderTop": "#000000",
		"tab.unfocusedActiveBorderTop": "#000000",
		"tab.lastPinnedBorder": "#000000",
		"tab.inactiveBackground": "#000000",
		"tab.unfocusedInactiveBackground": "#000000",
		"tab.inactiveForeground": "#a8a8a8",
		"tab.unfocusedActiveForeground": "#ffffff",
		"tab.unfocusedInactiveForeground": "#a8a8a8",
		"tab.hoverBackground": "#000000",
		"tab.unfocusedHoverBackground": "#000000",
		"tab.hoverForeground": "#ffffff",
		"tab.unfocusedHoverForeground": "#ffffff",
		"tab.hoverBorder": "#ffffff",
		"tab.unfocusedHoverBorder": "#000000",
		"tab.activeModifiedBorder": "#000000",
		"tab.inactiveModifiedBorder": "#000000",
		"tab.unfocusedInactiveModifiedBorder": "#000000",
		"tab.unfocusedActiveModifiedBorder": "#000000",
		"editorPane.background": "#000000",

		"pickerGroup.border": "#000000",
		"pickerGroup.foreground": "#ffffff",
		"quickInput.background": "#1e1e1e",
		"quickInput.foreground": "#b0b0b0",
		"quickInputList.focusBackground": "#1e1e1e",
		"quickInputList.focusForeground": "#ffffff",
		"quickInputList.focusIconForeground": "#ffffff",
		"quickInputTitle.background": "#1e1e1e",

		"textLink.activeForeground": "#ffffff",

		"toolbar.hoverBackground": "#000000",
		"toolbar.hoverOutline": "#ffffff",
		"toolbar.activeBackground": "#000000",

		"button.background": "#1d1d1d",
		"button.foreground": "#ffffff",

		"dropdown.background": "#000000",
		"dropdown.listBackground": "#000000",
		"dropdown.border": "#545454",
		"dropdown.foreground": "#c0c0c0",

		"panel.background": "#000000",
		"panel.border": "#232323",
		"panel.dropBorder": "#ffffff",
		"panelTitle.activeBorder": "#ffffff",
		"panelTitle.activeForeground": "#ffffff",
		"panelTitle.inactiveForeground": "#a8a8a8",

		"editorGroup.border": "#000000",
		"editorGroup.dropBackground": "#1e1e1e",
		"editorGroupHeader.noTabsBackground": "#000000",
		"editorGroupHeader.tabsBackground": "#000000",
		"editorGroupHeader.tabsBorder": "#000000",
		"editorGroupHeader.border": "#000000",
		"editorGroup.emptyBackground": "#000000",
		"editorGroup.focusedEmptyBorder": "#484848",
		"editorGroup.dropIntoPromptForeground": "#ffffff",

		"input.background": "#000000",
		"input.foreground": "#ffffff",
		"input.border": "#545454",
		"inputOption.activeBackground": "#000000",
		"inputOption.activeBorder": "#ffffff",
		"inputOption.activeForeground": "#ffffff",
		"inputOption.hoverBackground": "#000000",

		"list.activeSelectionBackground": "#3d3d3d",
		"list.activeSelectionForeground": "#ffffff",
		"list.activeSelectionIconForeground": "#ffffff",
		"list.dropBackground": "#000000",
		"list.focusBackground": "#000000",
		"list.focusForeground": "#ffffff",
		"list.focusHighlightForeground": "#ffffff",
		"list.focusOutline": "#ffffff",
		"list.focusAndSelectionOutline": "#000000",
		"list.highlightForeground": "#ffffff",
		"list.hoverBackground": "#000000",
		"list.hoverForeground": "#ffffff",
		"list.inactiveSelectionBackground": "#3d3d3d",
		"list.inactiveSelectionForeground": "#ffffff",
		"list.inactiveSelectionIconForeground": "#ffffff",
		"list.inactiveFocusBackground": "#000000",
		"list.inactiveFocusOutline": "#000000",
		"list.invalidItemForeground": "#ffffff",
		"list.errorForeground": "#ff8080",
		"list.warningForeground": "#ffdf7f",

		"gitDecoration.addedResourceForeground": "#ffffff",
		"gitDecoration.modifiedResourceForeground": "#ffffff",
		"gitDecoration.deletedResourceForeground": "#ffffff",
		"gitDecoration.renamedResourceForeground": "#ffffff",
		"gitDecoration.stageModifiedResourceForeground": "#ffffff",
		"gitDecoration.stageDeletedResourceForeground": "#ffffff",
		"gitDecoration.untrackedResourceForeground": "#ffffff",
		"gitDecoration.ignoredResourceForeground": "#646464",
		"gitDecoration.conflictingResourceForeground": "#ffce0c",
		"gitDecoration.submoduleResourceForeground": "#ffffff",

		"breadcrumb.activeSelectionForeground": "#ffffff",
		"focusBorder": "#ffffff",

	},
	"tokenColors": [
		{
			"name": "Comment",
			"scope": [
				"comment",
				"punctuation.definition.comment"
			],
			"settings": {
				"fontStyle": "italic",
				"foreground": "#646464"
			}
		},
		{
			"name": "Variables",
			"scope": [
				"variable",
				"string constant.other.placeholder"
			],
			"settings": {
				"foreground": "#a7a7a7"
			}
		},
		{
			"name": "Colors",
			"scope": [
				"constant.other.color"
			],
			"settings": {
				"foreground": "#ffffff"
			}
		},
		{
			"name": "Invalid",
			"scope": [
				"invalid",
				"invalid.illegal"
			],
			"settings": {
				"foreground": "#FF5370"
			}
		},
		{
			"name": "Keyword, Storage",
			"scope": [
				"keyword",
				"storage.type",
				"storage.modifier"
			],
			"settings": {
				"foreground": "#bd9aff"
			}
		},
		{
			"name": "Operator, Misc",
			"scope": [
				"keyword.control",
				"constant.other.color",
				"punctuation",
				"meta.tag",
				"punctuation.definition.tag",
				"punctuation.separator.inheritance.php",
				"punctuation.definition.tag.html",
				"punctuation.definition.tag.begin.html",
				"punctuation.definition.tag.end.html",
				"punctuation.section.embedded",
				"keyword.other.template",
				"keyword.other.substitution"
			],
			"settings": {
				"foreground": "#ffffff"
			}
		},
		{
			"name": "Tag",
			"scope": [
				"entity.name.tag",
				"meta.tag.sgml",
				"markup.deleted.git_gutter"
			],
			"settings": {
				"foreground": "#00bfff"
			}
		},
		{
			"name": "Function, Special Method",
			"scope": [
				"entity.name.function",
				"meta.function-call",
				"variable.function",
				"support.function",
				"keyword.other.special-method"
			],
			"settings": {
				"foreground": "#a0cd7c"
			}
		},
		{
			"name": "Block Level Variables",
			"scope": [
				"meta.block variable.other"
			],
			"settings": {
				"foreground": "#a7a7a7"
			}
		},
		{
			"name": "Other Variable, String Link",
			"scope": [
				"support.other.variable",
				"string.other.link"
			],
			"settings": {
				"foreground": "#86dbff"
			}
		},
		{
			"name": "Number, Constant, Function Argument, Tag Attribute, Embedded",
			"scope": [
				"constant.numeric",
				"constant.language",
				"support.constant",
				"constant.character",
				"constant.escape",
				// "variable.parameter",
				"keyword.other.unit",
				"keyword.other"
			],
			"settings": {
				"foreground": "#d8caa5"
			}
		},
		{
			"name": "String, Symbols, Markup Heading",
			"scope": [
				"string",
				"constant.other.symbol",
				"constant.other.key",
				"markup.heading",
				"markup.inserted.git_gutter",
				"meta.group.braces.curly constant.other.object.key.js string.unquoted.label.js"
			],
			"settings": {
				"foreground": "#d8caa5"
			}
		},
		{
			"name": "Class, Inherited Class, Support",
			"scope": [
				"entity.name",
				"support.type",
				"support.class",
				"support.other.namespace.use.php",
				"entity.other.inherited-class",
				"meta.use.php",
				"support.other.namespace.php",
				"markup.changed.git_gutter",
				"support.type.sys-types"
			],
			"settings": {
				"foreground": "#5cbcc7"
			}
		},
		{
			"name": "Entity Types",
			"scope": [
				"support.type"
			],
			"settings": {
				"foreground": "#00b7ff"
			}
		},
		{
			"name": "CSS Class and Support",
			"scope": [
				"source.css support.type.property-name",
				"source.sass support.type.property-name",
				"source.scss support.type.property-name",
				"source.less support.type.property-name",
				"source.stylus support.type.property-name",
				"source.postcss support.type.property-name"
			],
			"settings": {
				"foreground": "#B2CCD6"
			}
		},
		{
			"name": "Sub-methods",
			"scope": [
				"entity.name.module.js",
				"variable.import.parameter.js",
				"variable.other.class.js"
			],
			"settings": {
				"foreground": "#FF5370"
			}
		},
		{
			"name": "Language methods",
			"scope": [
				"variable.language"
			],
			"settings": {
				"fontStyle": "italic",
				"foreground": "#cc818d"
			}
		},
		{
			"name": "entity.name.method.js",
			"scope": [
				"entity.name.method.js"
			],
			"settings": {
				"fontStyle": "italic",
				"foreground": "#82AAFF"
			}
		},
		{
			"name": "meta.method.js",
			"scope": [
				"meta.class-method.js entity.name.function.js",
				"variable.function.constructor"
			],
			"settings": {
				"foreground": "#82AAFF"
			}
		},
		{
			"name": "Attributes",
			"scope": [
				"entity.other.attribute-name"
			],
			"settings": {
				"foreground": "#C792EA"
			}
		},
		{
			"name": "HTML Attributes",
			"scope": [
				"text.html.basic entity.other.attribute-name.html",
				"text.html.basic entity.other.attribute-name"
			],
			"settings": {
				"fontStyle": "italic",
				"foreground": "#FFCB6B"
			}
		},
		{
			"name": "CSS Classes",
			"scope": [
				"entity.other.attribute-name.class"
			],
			"settings": {
				"foreground": "#FFCB6B"
			}
		},
		{
			"name": "CSS ID's",
			"scope": [
				"source.sass keyword.control"
			],
			"settings": {
				"foreground": "#82AAFF"
			}
		},
		{
			"name": "Inserted",
			"scope": [
				"markup.inserted"
			],
			"settings": {
				"foreground": "#C3E88D"
			}
		},
		{
			"name": "Deleted",
			"scope": [
				"markup.deleted"
			],
			"settings": {
				"foreground": "#FF5370"
			}
		},
		{
			"name": "Changed",
			"scope": [
				"markup.changed"
			],
			"settings": {
				"foreground": "#C792EA"
			}
		},
		{
			"name": "Regular Expressions",
			"scope": [
				"string.regexp"
			],
			"settings": {
				"foreground": "#ffffff"
			}
		},
		{
			"name": "Escape Characters",
			"scope": [
				"constant.character.escape"
			],
			"settings": {
				"foreground": "#ffffff"
			}
		},
		{
			"name": "URL",
			"scope": [
				"*url*",
				"*link*",
				"*uri*"
			],
			"settings": {
				"fontStyle": "underline"
			}
		},
		{
			"name": "Decorators",
			"scope": [
				"tag.decorator.js entity.name.tag.js",
				"tag.decorator.js punctuation.definition.tag.js"
			],
			"settings": {
				"fontStyle": "italic",
				"foreground": "#82AAFF"
			}
		},
		{
			"name": "ES7 Bind Operator",
			"scope": [
				"source.js constant.other.object.key.js string.unquoted.label.js"
			],
			"settings": {
				"fontStyle": "italic",
				"foreground": "#FF5370"
			}
		},
		{
			"name": "JSON Key - Level 0",
			"scope": [
				"source.json meta.structure.dictionary.json support.type.property-name.json"
			],
			"settings": {
				"foreground": "#C792EA"
			}
		},
		{
			"name": "JSON Key - Level 1",
			"scope": [
				"source.json meta.structure.dictionary.json meta.structure.dictionary.value.json meta.structure.dictionary.json support.type.property-name.json"
			],
			"settings": {
				"foreground": "#FFCB6B"
			}
		},
		{
			"name": "JSON Key - Level 2",
			"scope": [
				"source.json meta.structure.dictionary.json meta.structure.dictionary.value.json meta.structure.dictionary.json meta.structure.dictionary.value.json meta.structure.dictionary.json support.type.property-name.json"
			],
			"settings": {
				"foreground": "#F78C6C"
			}
		},
		{
			"name": "JSON Key - Level 3",
			"scope": [
				"source.json meta.structure.dictionary.json meta.structure.dictionary.value.json meta.structure.dictionary.json meta.structure.dictionary.value.json meta.structure.dictionary.json meta.structure.dictionary.value.json meta.structure.dictionary.json support.type.property-name.json"
			],
			"settings": {
				"foreground": "#FF5370"
			}
		},
		{
			"name": "JSON Key - Level 4",
			"scope": [
				"source.json meta.structure.dictionary.json meta.structure.dictionary.value.json meta.structure.dictionary.json meta.structure.dictionary.value.json meta.structure.dictionary.json meta.structure.dictionary.value.json meta.structure.dictionary.json meta.structure.dictionary.value.json meta.structure.dictionary.json support.type.property-name.json"
			],
			"settings": {
				"foreground": "#C17E70"
			}
		},
		{
			"name": "JSON Key - Level 5",
			"scope": [
				"source.json meta.structure.dictionary.json meta.structure.dictionary.value.json meta.structure.dictionary.json meta.structure.dictionary.value.json meta.structure.dictionary.json meta.structure.dictionary.value.json meta.structure.dictionary.json meta.structure.dictionary.value.json meta.structure.dictionary.json meta.structure.dictionary.value.json meta.structure.dictionary.json support.type.property-name.json"
			],
			"settings": {
				"foreground": "#82AAFF"
			}
		},
		{
			"name": "JSON Key - Level 6",
			"scope": [
				"source.json meta.structure.dictionary.json meta.structure.dictionary.value.json meta.structure.dictionary.json meta.structure.dictionary.value.json meta.structure.dictionary.json meta.structure.dictionary.value.json meta.structure.dictionary.json meta.structure.dictionary.value.json meta.structure.dictionary.json meta.structure.dictionary.value.json meta.structure.dictionary.json meta.structure.dictionary.value.json meta.structure.dictionary.json support.type.property-name.json"
			],
			"settings": {
				"foreground": "#f07178"
			}
		},
		{
			"name": "JSON Key - Level 7",
			"scope": [
				"source.json meta.structure.dictionary.json meta.structure.dictionary.value.json meta.structure.dictionary.json meta.structure.dictionary.value.json meta.structure.dictionary.json meta.structure.dictionary.value.json meta.structure.dictionary.json meta.structure.dictionary.value.json meta.structure.dictionary.json meta.structure.dictionary.value.json meta.structure.dictionary.json meta.structure.dictionary.value.json meta.structure.dictionary.json meta.structure.dictionary.value.json meta.structure.dictionary.json support.type.property-name.json"
			],
			"settings": {
				"foreground": "#C792EA"
			}
		},
		{
			"name": "JSON Key - Level 8",
			"scope": [
				"source.json meta.structure.dictionary.json meta.structure.dictionary.value.json meta.structure.dictionary.json meta.structure.dictionary.value.json meta.structure.dictionary.json meta.structure.dictionary.value.json meta.structure.dictionary.json meta.structure.dictionary.value.json meta.structure.dictionary.json meta.structure.dictionary.value.json meta.structure.dictionary.json meta.structure.dictionary.value.json meta.structure.dictionary.json meta.structure.dictionary.value.json meta.structure.dictionary.json meta.structure.dictionary.value.json meta.structure.dictionary.json support.type.property-name.json"
			],
			"settings": {
				"foreground": "#C3E88D"
			}
		},
		{
			"name": "Markdown - Plain",
			"scope": [
				"text.html.markdown",
				"punctuation.definition.list_item.markdown"
			],
			"settings": {
				"foreground": "#EEFFFF"
			}
		},
		{
			"name": "Markdown - Markup Raw Inline",
			"scope": [
				"text.html.markdown markup.inline.raw.markdown"
			],
			"settings": {
				"foreground": "#C792EA"
			}
		},
		{
			"name": "Markdown - Markup Raw Inline Punctuation",
			"scope": [
				"text.html.markdown markup.inline.raw.markdown punctuation.definition.raw.markdown"
			],
			"settings": {
				"foreground": "#65737E"
			}
		},
		{
			"name": "Markdown - Heading",
			"scope": [
				"markdown.heading",
				"markup.heading | markup.heading entity.name",
				"markup.heading.markdown punctuation.definition.heading.markdown"
			],
			"settings": {
				"foreground": "#C3E88D"
			}
		},
		{
			"name": "Markup - Italic",
			"scope": [
				"markup.italic"
			],
			"settings": {
				"fontStyle": "italic",
				"foreground": "#f07178"
			}
		},
		{
			"name": "Markup - Bold",
			"scope": [
				"markup.bold",
				"markup.bold string"
			],
			"settings": {
				"fontStyle": "bold",
				"foreground": "#f07178"
			}
		},
		{
			"name": "Markup - Bold-Italic",
			"scope": [
				"markup.bold markup.italic",
				"markup.italic markup.bold",
				"markup.quote markup.bold",
				"markup.bold markup.italic string",
				"markup.italic markup.bold string",
				"markup.quote markup.bold string"
			],
			"settings": {
				"fontStyle": "bold",
				"foreground": "#f07178"
			}
		},
		{
			"name": "Markup - Underline",
			"scope": [
				"markup.underline"
			],
			"settings": {
				"fontStyle": "underline",
				"foreground": "#F78C6C"
			}
		},
		{
			"name": "Markdown - Blockquote",
			"scope": [
				"markup.quote punctuation.definition.blockquote.markdown"
			],
			"settings": {
				"foreground": "#65737E"
			}
		},
		{
			"name": "Markup - Quote",
			"scope": [
				"markup.quote"
			],
			"settings": {
				"fontStyle": "italic"
			}
		},
		{
			"name": "Markdown - Link",
			"scope": [
				"string.other.link.title.markdown"
			],
			"settings": {
				"foreground": "#82AAFF"
			}
		},
		{
			"name": "Markdown - Link Description",
			"scope": [
				"string.other.link.description.title.markdown"
			],
			"settings": {
				"foreground": "#C792EA"
			}
		},
		{
			"name": "Markdown - Link Anchor",
			"scope": [
				"constant.other.reference.link.markdown"
			],
			"settings": {
				"foreground": "#FFCB6B"
			}
		},
		{
			"name": "Markup - Raw Block",
			"scope": [
				"markup.raw.block"
			],
			"settings": {
				"foreground": "#C792EA"
			}
		},
		{
			"name": "Markdown - Raw Block Fenced",
			"scope": [
				"markup.raw.block.fenced.markdown"
			],
			"settings": {
				"foreground": "#00000050"
			}
		},
		{
			"name": "Markdown - Fenced Bode Block",
			"scope": [
				"punctuation.definition.fenced.markdown"
			],
			"settings": {
				"foreground": "#00000050"
			}
		},
		{
			"name": "Markdown - Fenced Bode Block Variable",
			"scope": [
				"markup.raw.block.fenced.markdown",
				"variable.language.fenced.markdown",
				"punctuation.section.class.end"
			],
			"settings": {
				"foreground": "#EEFFFF"
			}
		},
		{
			"name": "Markdown - Fenced Language",
			"scope": [
				"variable.language.fenced.markdown"
			],
			"settings": {
				"foreground": "#65737E"
			}
		},
		{
			"name": "Markdown - Separator",
			"scope": [
				"meta.separator"
			],
			"settings": {
				"fontStyle": "bold",
				"foreground": "#65737E"
			}
		},
		{
			"name": "Markup - Table",
			"scope": [
				"markup.table"
			],
			"settings": {
				"foreground": "#EEFFFF"
			}
		}
	]
}
